README.md
setup.py
bin/gevo-analyze
bin/gevo-evaluate
bin/gevo-evolve
bin/gevo-explore
bin/gevo-reduce
bin/gevo-stage-analyze
fuzzycompare/fuzzycompare.cpp
gevo/__init__.py
gevo/evolve.py
gevo/irind.py
gevo.egg-info/PKG-INFO
gevo.egg-info/SOURCES.txt
gevo.egg-info/dependency_links.txt
gevo.egg-info/not-zip-safe
gevo.egg-info/requires.txt
gevo.egg-info/top_level.txt